[
  {
    "footer": "",
    "header": "",
    "id": null,
    "name": "",
    "py/object": "model.group.Group"
  },
  {
    "footer": "footer<_K_ ",
    "header": "headerJ_4_A_ _P_|_\\_U_u",
    "id": null,
    "name": "name6_p_A_j_i_x_M",
    "py/object": "model.group.Group"
  },
  {
    "footer": "footerC_)",
    "header": "header8_+_c_Y",
    "id": null,
    "name": "name=_]_D_x_(",
    "py/object": "model.group.Group"
  },
  {
    "footer": "footero_$_T_|_o_t_ _ _w",
    "header": "headerL_o_g_x_a_ _#",
    "id": null,
    "name": "namer",
    "py/object": "model.group.Group"
  },
  {
    "footer": "footer4_s_ _O_H_|_7_ _L_ _C_._ _<_._ _g",
    "header": "header|_G_]_|_t_(_G_1_E_ _4_B_._C_)_ _v_N",
    "id": null,
    "name": "namev_*_,",
    "py/object": "model.group.Group"
  },
  {
    "footer": "footer _a_&_l_`_u_!_c_^_l_._g_=_L_x_8_.",
    "header": "header:_|_6_0_0_X_<_f_O_2",
    "id": null,
    "name": "nameE",
    "py/object": "model.group.Group"
  }
]